{
  "teleports": [
    {
      "time": "80.25616",
      "teleportTime": "1.903121",
      "teleportType": "circle",
      "exhibition": "Earth",
      "prePositions": [
        {
          "x": 12.815009117126465,
          "y": 1.970978021621704,
          "z": -5.630914688110352
        },
        {
          "x": 10.239550590515137,
          "y": 2.0518200397491457,
          "z": -6.705323219299316
        },
        {
          "x": 9.505826950073243,
          "y": 2.0330612659454347,
          "z": -9.404081344604493
        },
        {
          "x": 11.965280532836914,
          "y": 2.0300374031066896,
          "z": -10.702862739562989
        },
        {
          "x": 14.044073104858399,
          "y": 2.0300374031066896,
          "z": -8.983128547668457
        }
      ],
      "nextPositons": [
        {
          "x": 10.642202377319336,
          "y": 2.0300374031066896,
          "z": 2.251224994659424
        },
        {
          "x": 7.949590682983398,
          "y": 2.0300374031066896,
          "z": 2.0818142890930177
        },
        {
          "x": 7.278646469116211,
          "y": 2.0300374031066896,
          "z": -0.5313626527786255
        },
        {
          "x": 9.556591987609864,
          "y": 2.0300374031066896,
          "z": -1.9769842624664307
        },
        {
          "x": 11.635384559631348,
          "y": 2.0300374031066896,
          "z": -0.25725021958351138
        }
      ],
      "preForwards": [
        {
          "x": -0.38449206948280337,
          "y": -0.18534407019615174,
          "z": 0.9043303728103638
        },
        {
          "x": -0.47345489263534548,
          "y": 0.042841535061597827,
          "z": -0.8797755241394043
        },
        {
          "x": 0.3860827386379242,
          "y": -0.10923191159963608,
          "z": 0.9159740805625916
        },
        {
          "x": -0.10160736739635468,
          "y": 0.0,
          "z": 0.9948245882987976
        },
        {
          "x": -0.28981396555900576,
          "y": 0.0,
          "z": 0.957082986831665
        }
      ],
      "nextForwards": [
        {
          "x": -0.5358251333236694,
          "y": 0.0,
          "z": -0.8443291187286377
        },
        {
          "x": 0.6374255418777466,
          "y": 0.0,
          "z": -0.7705121040344238
        },
        {
          "x": 0.9297757744789124,
          "y": 0.0,
          "z": 0.36812645196914675
        },
        {
          "x": -0.06279242038726807,
          "y": 0.0,
          "z": 0.9980266094207764
        },
        {
          "x": -0.9685838222503662,
          "y": 0.0,
          "z": 0.24868768453598023
        }
      ],
      "offsetAngles": [ 124.56647802711814, 67.88721804767192, 45.544480558842227, 2.231603187575004, 58.75331524702233 ],
      "qualities": [
        {
          "size_quality": 0.1173858642578125,
          "depth_quality": 0.05713755632569075,
          "colorfulness_quality": 0.1022048346558238,
          "covered_quality": 1.0,
          "integrity_quality": 0.6995583772659302
        },
        {
          "size_quality": 0.10981178283691406,
          "depth_quality": 0.04756911613982243,
          "colorfulness_quality": 0.10804551243493019,
          "covered_quality": 1.0,
          "integrity_quality": 0.8933664560317993
        },
        {
          "size_quality": 0.096954345703125,
          "depth_quality": 0.039989824233571797,
          "colorfulness_quality": 0.084265662959679,
          "covered_quality": 1.0,
          "integrity_quality": 0.996989369392395
        },
        {
          "size_quality": 0.10528373718261719,
          "depth_quality": 0.04441831200810865,
          "colorfulness_quality": 0.08153849388901535,
          "covered_quality": 1.0,
          "integrity_quality": 0.9463064074516296
        },
        {
          "size_quality": 0.11651420593261719,
          "depth_quality": 0.05504942188594042,
          "colorfulness_quality": 0.10067650116566335,
          "covered_quality": 1.0,
          "integrity_quality": 0.7440333962440491
        }
      ],
      "finalQualities": [ 0.869213707486884, 0.9238916551787666, 0.8868779796876491, 0.8777706681647377, 0.8767520754295741 ]
    },
    {
      "time": "100.9607",
      "teleportTime": "12.5852",
      "teleportType": "horseshoe",
      "exhibition": "Paint1",
      "prePositions": [
        {
          "x": 9.859965324401856,
          "y": 1.967789888381958,
          "z": 2.627617835998535
        },
        {
          "x": 8.04582691192627,
          "y": 2.0230612754821779,
          "z": 2.135918140411377
        },
        {
          "x": 7.455826759338379,
          "y": 2.013061285018921,
          "z": -0.42408180236816409
        },
        {
          "x": 9.556591987609864,
          "y": 2.0300374031066896,
          "z": -1.9769842624664307
        },
        {
          "x": 11.635384559631348,
          "y": 2.0300374031066896,
          "z": -0.25725021958351138
        }
      ],
      "nextPositons": [
        {
          "x": 2.236461639404297,
          "y": 2.0300374031066896,
          "z": 11.166377067565918
        },
        {
          "x": 2.9197769165039064,
          "y": 2.0300374031066896,
          "z": 9.923433303833008
        },
        {
          "x": 4.203174591064453,
          "y": 2.0300374031066896,
          "z": 9.319514274597168
        },
        {
          "x": 5.596439361572266,
          "y": 2.0300374031066896,
          "z": 9.585294723510743
        },
        {
          "x": 6.5673933029174809,
          "y": 2.0300374031066896,
          "z": 10.619256973266602
        }
      ],
      "preForwards": [
        {
          "x": -0.504265546798706,
          "y": -0.22744914889335633,
          "z": 0.8330565690994263
        },
        {
          "x": 0.9343180060386658,
          "y": -0.02431858330965042,
          "z": 0.35561031103134158
        },
        {
          "x": 0.7403225302696228,
          "y": -0.29657217860221865,
          "z": -0.6032971143722534
        },
        {
          "x": -0.4865702688694,
          "y": 0.0,
          "z": 0.8736414909362793
        },
        {
          "x": -0.6353539824485779,
          "y": 0.0,
          "z": 0.772221028804779
        }
      ],
      "nextForwards": [
        {
          "x": 0.9822872877120972,
          "y": 0.0,
          "z": 0.18738192319869996
        },
        {
          "x": 0.6845464706420898,
          "y": 0.0,
          "z": 0.7289692163467407
        },
        {
          "x": 0.1253322958946228,
          "y": 0.0,
          "z": 0.9921148419380188
        },
        {
          "x": -0.4817543923854828,
          "y": 0.0,
          "z": 0.8763062953948975
        },
        {
          "x": -0.9048274755477905,
          "y": 0.0,
          "z": 0.4257783889770508
        }
      ],
      "offsetAngles": [ 110.38731250317369, 25.962744621381263, 121.97703033913513, 0.3146578007512879, 25.35381788184111 ],
      "qualities": [
        {
          "size_quality": 0.19611644744873048,
          "depth_quality": 0.04648351748614585,
          "colorfulness_quality": 0.13798760249264836,
          "covered_quality": 1.0,
          "integrity_quality": 0.5364212989807129
        },
        {
          "size_quality": 0.2668466567993164,
          "depth_quality": 0.04407145008996852,
          "colorfulness_quality": 0.14091047691378306,
          "covered_quality": 1.0,
          "integrity_quality": 0.8950536847114563
        },
        {
          "size_quality": 0.2511262893676758,
          "depth_quality": 0.039088727871973847,
          "colorfulness_quality": 0.13827439123365163,
          "covered_quality": 0.9999961853027344,
          "integrity_quality": 0.9995824694633484
        },
        {
          "size_quality": 0.26076507568359377,
          "depth_quality": 0.045277417815426417,
          "colorfulness_quality": 0.13910228677386286,
          "covered_quality": 1.0,
          "integrity_quality": 0.9387578368186951
        },
        {
          "size_quality": 0.18051815032958985,
          "depth_quality": 0.04728100687542701,
          "colorfulness_quality": 0.13437469798075728,
          "covered_quality": 1.0,
          "integrity_quality": 0.5235155820846558
        }
      ],
      "finalQualities": [ 0.677678731011857, 0.7950794918910566, 0.8192627226598185, 0.8049329077919958, 0.667152053325418 ]
    },
    {
      "time": "118.7864",
      "teleportTime": "9.701789",
      "teleportType": "circle",
      "exhibition": "Vaes2",
      "prePositions": [
        {
          "x": 1.933792233467102,
          "y": 1.9409863948822022,
          "z": 10.408243179321289
        },
        {
          "x": 2.825827121734619,
          "y": 1.9630613327026368,
          "z": 9.675917625427246
        },
        {
          "x": 4.285827159881592,
          "y": 2.0530612468719484,
          "z": 8.72591781616211
        },
        {
          "x": 5.596439361572266,
          "y": 2.0300374031066896,
          "z": 9.585294723510743
        },
        {
          "x": 6.5673933029174809,
          "y": 2.0300374031066896,
          "z": 10.619256973266602
        }
      ],
      "nextPositons": [
        {
          "x": -0.0832822322845459,
          "y": 2.0300374031066896,
          "z": 9.074481964111329
        },
        {
          "x": 1.279275894165039,
          "y": 2.0300374031066896,
          "z": 7.794956684112549
        },
        {
          "x": 2.9172301292419435,
          "y": 2.0300374031066896,
          "z": 8.69543170928955
        },
        {
          "x": 2.566983222961426,
          "y": 2.0300374031066896,
          "z": 10.53148078918457
        },
        {
          "x": 0.7125643491744995,
          "y": 2.0300374031066896,
          "z": 10.765746116638184
        }
      ],
      "preForwards": [
        {
          "x": -0.7995071411132813,
          "y": -0.4211564362049103,
          "z": -0.42827072739601138
        },
        {
          "x": -0.21055205166339875,
          "y": -0.5217698812484741,
          "z": -0.8266948461532593
        },
        {
          "x": -0.6859737634658814,
          "y": -0.07909175753593445,
          "z": 0.7233148813247681
        },
        {
          "x": -0.9959801435470581,
          "y": 0.0,
          "z": -0.08957457542419434
        },
        {
          "x": -0.974069356918335,
          "y": 0.0,
          "z": -0.22625041007995606
        }
      ],
      "nextForwards": [
        {
          "x": 0.9822873473167419,
          "y": 0.0,
          "z": 0.18738174438476563
        },
        {
          "x": 0.1253323256969452,
          "y": 0.0,
          "z": 0.9921148419380188
        },
        {
          "x": -0.9048275947570801,
          "y": 0.0,
          "z": 0.42577826976776125
        },
        {
          "x": -0.6845464706420898,
          "y": 0.0,
          "z": -0.7289695739746094
        },
        {
          "x": 0.48175475001335146,
          "y": 0.0,
          "z": -0.876306414604187
        }
      ],
      "offsetAngles": [ 162.62348656433916, 172.91099466889137, 21.317836856054556, 41.66092715899481, 105.72364562307257 ],
      "qualities": [
        {
          "size_quality": 0.022220611572265626,
          "depth_quality": 0.0240684825776882,
          "colorfulness_quality": 0.07657585031173846,
          "covered_quality": 1.0,
          "integrity_quality": 1.0004723072052003
        },
        {
          "size_quality": 0.0206756591796875,
          "depth_quality": 0.022489519413533417,
          "colorfulness_quality": 0.06816464286295401,
          "covered_quality": 1.0,
          "integrity_quality": 0.9999077320098877
        },
        {
          "size_quality": 0.03443622589111328,
          "depth_quality": 0.03834937241168744,
          "colorfulness_quality": 0.0718008899077263,
          "covered_quality": 1.0,
          "integrity_quality": 0.8964053392410278
        },
        {
          "size_quality": 0.02836894989013672,
          "depth_quality": 0.04406243228171751,
          "colorfulness_quality": 0.0742055061488979,
          "covered_quality": 1.0,
          "integrity_quality": 0.42210492491722109
        },
        {
          "size_quality": 0.03532695770263672,
          "depth_quality": 0.04157149734488895,
          "colorfulness_quality": 0.09064810919229939,
          "covered_quality": 1.0,
          "integrity_quality": 0.7914325594902039
        }
      ],
      "finalQualities": [ 0.894806779115789, 0.8654215153958298, 0.912010220357556, 0.7652224271420769, 0.937368584118037 ]
    },
    {
      "time": "142.2467",
      "teleportTime": "6.803005",
      "teleportType": "circle",
      "exhibition": "AH64 Prefab",
      "prePositions": [
        {
          "x": -1.0145063400268555,
          "y": 1.9622647762298585,
          "z": 4.249016284942627
        },
        {
          "x": -0.724172830581665,
          "y": 2.013061285018921,
          "z": 4.225917816162109
        },
        {
          "x": 0.09582734107971192,
          "y": 2.0330612659454347,
          "z": 4.775918006896973
        },
        {
          "x": 0.194970041513443,
          "y": 2.0300374031066896,
          "z": 4.830196857452393
        },
        {
          "x": 0.6466859579086304,
          "y": 2.0300374031066896,
          "z": 5.116864204406738
        }
      ],
      "nextPositons": [
        {
          "x": -3.307459831237793,
          "y": 2.0300374031066896,
          "z": 3.1880359649658205
        },
        {
          "x": -6.045472621917725,
          "y": 2.0300374031066896,
          "z": 4.272092819213867
        },
        {
          "x": -7.922564506530762,
          "y": 2.0300374031066896,
          "z": 2.003080368041992
        },
        {
          "x": -6.344658851623535,
          "y": 2.0300374031066896,
          "z": -0.4833033084869385
        },
        {
          "x": -3.4923667907714845,
          "y": 2.0300374031066896,
          "z": 0.2490394115447998
        }
      ],
      "preForwards": [
        {
          "x": -0.9232501983642578,
          "y": -0.25664013624191286,
          "z": -0.285910964012146
        },
        {
          "x": -0.8235263228416443,
          "y": -0.20114582777023316,
          "z": -0.5304197072982788
        },
        {
          "x": -0.9270215630531311,
          "y": -0.07256092131137848,
          "z": -0.36792081594467165
        },
        {
          "x": -0.9054195284843445,
          "y": 0.0,
          "z": -0.42451798915863039
        },
        {
          "x": -0.8987705707550049,
          "y": 0.0,
          "z": -0.4384196996688843
        }
      ],
      "nextForwards": [
        {
          "x": -0.8443284034729004,
          "y": 0.0,
          "z": -0.5358266830444336
        },
        {
          "x": 0.24868960678577424,
          "y": 0.0,
          "z": -0.9685834646224976
        },
        {
          "x": 0.9980267882347107,
          "y": 0.0,
          "z": -0.06279122829437256
        },
        {
          "x": 0.3681250214576721,
          "y": 0.0,
          "z": 0.9297763109207153
        },
        {
          "x": -0.7705132365226746,
          "y": 0.0,
          "z": 0.637424111366272
        }
      ],
      "offsetAngles": [ 15.193344467144812, 71.61506703828764, 154.75258137861602, 136.72018507999838, 65.60310030972005 ],
      "qualities": [
        {
          "size_quality": 0.08517837524414063,
          "depth_quality": 0.039278005275772697,
          "colorfulness_quality": 0.09103099831632955,
          "covered_quality": 1.0,
          "integrity_quality": 0.9786124229431152
        },
        {
          "size_quality": 0.09998226165771485,
          "depth_quality": 0.04160679430652983,
          "colorfulness_quality": 0.09446152696693974,
          "covered_quality": 1.0,
          "integrity_quality": 0.8332260251045227
        },
        {
          "size_quality": 0.05052661895751953,
          "depth_quality": 0.03506621696922278,
          "colorfulness_quality": 0.08738641144512388,
          "covered_quality": 1.0,
          "integrity_quality": 0.5613464713096619
        },
        {
          "size_quality": 0.08794403076171875,
          "depth_quality": 0.03579625282357796,
          "colorfulness_quality": 0.08921930000905304,
          "covered_quality": 1.0,
          "integrity_quality": 0.9080399870872498
        },
        {
          "size_quality": 0.0764303207397461,
          "depth_quality": 0.03589321416280616,
          "colorfulness_quality": 0.08887102207791678,
          "covered_quality": 1.0,
          "integrity_quality": 0.9992892742156982
        }
      ],
      "finalQualities": [ 0.9046450236632144, 0.884621236021381, 0.7401432645254978, 0.8784588652163625, 0.8949404718995166 ]
    },
    {
      "time": "160.6325",
      "teleportTime": "5.954674",
      "teleportType": "horseshoe",
      "exhibition": "Paint2",
      "prePositions": [
        {
          "x": -0.7335147857666016,
          "y": 1.960890293121338,
          "z": -4.127719879150391
        },
        {
          "x": -1.5241727828979493,
          "y": 2.0330612659454347,
          "z": -3.174081802368164
        },
        {
          "x": -2.1741726398468019,
          "y": 2.0530612468719484,
          "z": -2.37408185005188
        },
        {
          "x": -2.9260571002960207,
          "y": 2.0300374031066896,
          "z": -1.7246170043945313
        },
        {
          "x": -3.6208744049072267,
          "y": 2.0300374031066896,
          "z": -0.984715461730957
        }
      ],
      "nextPositons": [
        {
          "x": 4.638442039489746,
          "y": 2.0300374031066896,
          "z": -7.03426456451416
        },
        {
          "x": 4.187366485595703,
          "y": 2.0300374031066896,
          "z": -6.213759422302246
        },
        {
          "x": 3.340157985687256,
          "y": 2.0300374031066896,
          "z": -5.815092086791992
        },
        {
          "x": 2.4204213619232179,
          "y": 2.0300374031066896,
          "z": -5.990540504455566
        },
        {
          "x": 1.7794642448425294,
          "y": 2.0300374031066896,
          "z": -6.673089027404785
        }
      ],
      "preForwards": [
        {
          "x": 0.6665943264961243,
          "y": -0.26893919706344607,
          "z": -0.6952149868011475
        },
        {
          "x": 0.6837883591651917,
          "y": -0.062417931854724887,
          "z": -0.7270059585571289
        },
        {
          "x": 0.7885456681251526,
          "y": 0.0351397804915905,
          "z": -0.6139715909957886
        },
        {
          "x": 0.8184943199157715,
          "y": 0.0,
          "z": -0.5745148658752441
        },
        {
          "x": 0.8067441582679749,
          "y": 0.0,
          "z": -0.5909010171890259
        }
      ],
      "nextForwards": [
        {
          "x": -0.982287585735321,
          "y": 0.0,
          "z": -0.18738043308258058
        },
        {
          "x": -0.6845477819442749,
          "y": 0.0,
          "z": -0.7289680242538452
        },
        {
          "x": -0.1253342181444168,
          "y": 0.0,
          "z": -0.9921146631240845
        },
        {
          "x": 0.48175278306007388,
          "y": 0.0,
          "z": -0.8763073682785034
        },
        {
          "x": 0.9048267006874085,
          "y": 0.0,
          "z": -0.4257800579071045
        }
      ],
      "offsetAngles": [ 122.99606725443937, 86.44542963549157, 59.295283933799968, 26.134395814963797, 11.020944071473196 ],
      "qualities": [
        {
          "size_quality": 0.2142791748046875,
          "depth_quality": 0.07199883068611293,
          "colorfulness_quality": 0.15927051789899156,
          "covered_quality": 1.0,
          "integrity_quality": 0.483081579208374
        },
        {
          "size_quality": 0.2986745834350586,
          "depth_quality": 0.06711538506167009,
          "colorfulness_quality": 0.1702917131908644,
          "covered_quality": 1.0,
          "integrity_quality": 0.6375875473022461
        },
        {
          "size_quality": 0.3486776351928711,
          "depth_quality": 0.05897920712248739,
          "colorfulness_quality": 0.17412958220800776,
          "covered_quality": 0.9964169859886169,
          "integrity_quality": 0.9075552821159363
        },
        {
          "size_quality": 0.2517728805541992,
          "depth_quality": 0.05511696146565853,
          "colorfulness_quality": 0.17153128321083725,
          "covered_quality": 0.9742881655693054,
          "integrity_quality": 1.0001022815704346
        },
        {
          "size_quality": 0.17013072967529298,
          "depth_quality": 0.059212560888643819,
          "colorfulness_quality": 0.15947605268411597,
          "covered_quality": 0.9038369655609131,
          "integrity_quality": 0.9914193153381348
        }
      ],
      "finalQualities": [ 0.6466633816509518, 0.7122442192961538, 0.7983277619538319, 0.8039051755355693, 0.7595289321228662 ]
    },
    {
      "time": "184.7835",
      "teleportTime": "1.830178",
      "teleportType": "auto",
      "exhibition": "Earth",
      "prePositions": [
        {
          "x": 14.102507591247559,
          "y": 1.9685869216918946,
          "z": -5.1500139236450199
        },
        {
          "x": 11.734107971191407,
          "y": 2.003061294555664,
          "z": -6.364081382751465
        },
        {
          "x": 9.355827331542969,
          "y": 2.0230612754821779,
          "z": -7.6337785720825199
        },
        {
          "x": 10.174530982971192,
          "y": 2.0300374031066896,
          "z": -9.891622543334961
        },
        {
          "x": 12.483806610107422,
          "y": 2.0300374031066896,
          "z": -10.183354377746582
        }
      ],
      "nextPositons": [
        {
          "x": 8.960000038146973,
          "y": 2.0300300121307375,
          "z": 2.8702216148376467
        },
        {
          "x": 7.659999847412109,
          "y": 2.0300300121307375,
          "z": 1.970221757888794
        },
        {
          "x": 8.260000228881836,
          "y": 2.0300300121307375,
          "z": 2.470221757888794
        },
        {
          "x": 12.059999465942383,
          "y": 2.0300300121307375,
          "z": -0.12977831065654756
        },
        {
          "x": 12.15999984741211,
          "y": 2.0300300121307375,
          "z": 0.6702216863632202
        }
      ],
      "preForwards": [
        {
          "x": -0.65755695104599,
          "y": -0.2097216695547104,
          "z": 0.7236268520355225
        },
        {
          "x": 0.21287545561790467,
          "y": -0.07350239157676697,
          "z": 0.9743107557296753
        },
        {
          "x": 0.952782154083252,
          "y": -0.14289163053035737,
          "z": -0.2679331600666046
        },
        {
          "x": 0.19617295265197755,
          "y": 0.0,
          "z": 0.9805693030357361
        },
        {
          "x": -0.06714162975549698,
          "y": 0.0,
          "z": 0.9977434277534485
        }
      ],
      "nextForwards": [
        {
          "x": 0.27999991178512576,
          "y": 0.0,
          "z": -0.9600001573562622
        },
        {
          "x": 0.800000011920929,
          "y": 0.0,
          "z": -0.5999999046325684
        },
        {
          "x": 0.573462188243866,
          "y": 0.0,
          "z": -0.8192319869995117
        },
        {
          "x": -0.9701426029205322,
          "y": 0.0,
          "z": 0.24253559112548829
        },
        {
          "x": -0.9968152642250061,
          "y": 0.0,
          "z": -0.07974517345428467
        }
      ],
      "offsetAngles": [ 153.99889731566419, 114.54512190706055, 39.301397301536557, 87.27701200683669, 90.72409240796333 ],
      "qualities": [
        {
          "size_quality": 0.10165596008300781,
          "depth_quality": 0.04244826905128645,
          "colorfulness_quality": 0.1034805460170416,
          "covered_quality": 1.0,
          "integrity_quality": 0.9726262092590332
        },
        {
          "size_quality": 0.10164546966552735,
          "depth_quality": 0.04244677717180426,
          "colorfulness_quality": 0.10268324026009168,
          "covered_quality": 1.0,
          "integrity_quality": 0.9725258946418762
        },
        {
          "size_quality": 0.10449504852294922,
          "depth_quality": 0.044181300741005357,
          "colorfulness_quality": 0.1060342187550109,
          "covered_quality": 1.0,
          "integrity_quality": 0.9485106468200684
        },
        {
          "size_quality": 0.1029653549194336,
          "depth_quality": 0.043219510297131179,
          "colorfulness_quality": 0.09428039941960286,
          "covered_quality": 1.0,
          "integrity_quality": 0.9625386595726013
        },
        {
          "size_quality": 0.10124778747558594,
          "depth_quality": 0.04221336427368579,
          "colorfulness_quality": 0.09475562017986999,
          "covered_quality": 1.0,
          "integrity_quality": 0.9756917953491211
        }
      ],
      "finalQualities": [ 0.925963169147803, 0.924270019591716, 0.928227086424511, 0.905786086114118, 0.9082108518530212 ]
    },
    {
      "time": "194.8299",
      "teleportTime": "1.356553",
      "teleportType": "auto",
      "exhibition": "Paint1",
      "prePositions": [
        {
          "x": 6.502152442932129,
          "y": 1.9651925563812256,
          "z": 5.561408042907715
        },
        {
          "x": 7.035826683044434,
          "y": 2.0230612754821779,
          "z": 5.615918159484863
        },
        {
          "x": 7.4258270263671879,
          "y": 2.0330612659454347,
          "z": 4.865918159484863
        },
        {
          "x": 6.4938201904296879,
          "y": 2.0300374031066896,
          "z": 6.088923454284668
        },
        {
          "x": 6.9938201904296879,
          "y": 2.0300374031066896,
          "z": 6.088923454284668
        }
      ],
      "nextPositons": [
        {
          "x": 2.7083675861358644,
          "y": 2.0300300121307375,
          "z": 11.581777572631836
        },
        {
          "x": 5.308367729187012,
          "y": 2.0300300121307375,
          "z": 10.481778144836426
        },
        {
          "x": 4.108367443084717,
          "y": 2.0300300121307375,
          "z": 10.681777954101563
        },
        {
          "x": 7.208367347717285,
          "y": 2.0300300121307375,
          "z": 10.081777572631836
        },
        {
          "x": 3.3083674907684328,
          "y": 2.0300300121307375,
          "z": 10.781778335571289
        }
      ],
      "preForwards": [
        {
          "x": -0.36907291412353518,
          "y": -0.23265673220157624,
          "z": 0.8998088836669922
        },
        {
          "x": -0.5602186918258667,
          "y": -0.08927971124649048,
          "z": 0.8235194087028503
        },
        {
          "x": -0.42751210927963259,
          "y": -0.12881144881248475,
          "z": 0.894785463809967
        },
        {
          "x": -0.4624985456466675,
          "y": 0.0,
          "z": 0.886620044708252
        },
        {
          "x": -0.5169947743415833,
          "y": 0.0,
          "z": 0.8559885621070862
        }
      ],
      "nextForwards": [
        {
          "x": 0.865426242351532,
          "y": 0.0,
          "z": 0.5010363459587097
        },
        {
          "x": -0.30320385098457339,
          "y": 0.0,
          "z": 0.9529257416725159
        },
        {
          "x": 0.24253563582897187,
          "y": 0.0,
          "z": 0.9701424837112427
        },
        {
          "x": -0.7071067094802856,
          "y": 0.0,
          "z": 0.7071068286895752
        },
        {
          "x": 0.5646840333938599,
          "y": 0.0,
          "z": 0.8253071904182434
        }
      ],
      "offsetAngles": [ 82.23328607612302, 16.576288743033275, 39.573863795992568, 17.45154675953586, 65.51123426431104 ],
      "qualities": [
        {
          "size_quality": 0.556035041809082,
          "depth_quality": 0.09020721228165865,
          "colorfulness_quality": 0.1406991437728226,
          "covered_quality": 0.9877059459686279,
          "integrity_quality": 0.9932589530944824
        },
        {
          "size_quality": 0.5367841720581055,
          "depth_quality": 0.07424394932001388,
          "colorfulness_quality": 0.14289771762776244,
          "covered_quality": 0.9999982118606567,
          "integrity_quality": 0.9955921173095703
        },
        {
          "size_quality": 0.6907930374145508,
          "depth_quality": 0.06926218987203083,
          "colorfulness_quality": 0.142501362359181,
          "covered_quality": 1.0,
          "integrity_quality": 0.9911889433860779
        },
        {
          "size_quality": 0.1269845962524414,
          "depth_quality": 0.030573155914223519,
          "colorfulness_quality": 0.11831036508577345,
          "covered_quality": 0.9681344032287598,
          "integrity_quality": 1.001112699508667
        },
        {
          "size_quality": 0.5485868453979492,
          "depth_quality": 0.07057492866596993,
          "colorfulness_quality": 0.14327497419434613,
          "covered_quality": 0.9999982714653015,
          "integrity_quality": 0.9949219226837158
        }
      ],
      "finalQualities": [ 0.8635075020287348, 0.8653586351005107, 0.8806091551539181, 0.7660415354152153, 0.8663280932426907 ]
    },
    {
      "time": "202.7415",
      "teleportTime": "1.107988",
      "teleportType": "auto",
      "exhibition": "Vaes2",
      "prePositions": [
        {
          "x": 2.4786314964294435,
          "y": 1.9374172687530518,
          "z": 10.934004783630371
        },
        {
          "x": 5.255826950073242,
          "y": 2.013061285018921,
          "z": 10.335917472839356
        },
        {
          "x": 3.9358272552490236,
          "y": 2.0530612468719484,
          "z": 10.7559175491333
        },
        {
          "x": 7.208367347717285,
          "y": 2.0300300121307375,
          "z": 10.081777572631836
        },
        {
          "x": 3.3083674907684328,
          "y": 2.0300300121307375,
          "z": 10.781778335571289
        }
      ],
      "nextPositons": [
        {
          "x": 0.24100056290626527,
          "y": 2.0300300121307375,
          "z": 10.327999114990235
        },
        {
          "x": 1.3410005569458008,
          "y": 2.0300300121307375,
          "z": 11.327999114990235
        },
        {
          "x": 0.24100056290626527,
          "y": 2.0300300121307375,
          "z": 9.127998352050782
        },
        {
          "x": 3.341000556945801,
          "y": 2.0300300121307375,
          "z": 10.127998352050782
        },
        {
          "x": 1.3410005569458008,
          "y": 2.0300300121307375,
          "z": 8.127998352050782
        }
      ],
      "preForwards": [
        {
          "x": -0.6109640002250671,
          "y": -0.4329832196235657,
          "z": -0.6627586483955383
        },
        {
          "x": -0.9396510720252991,
          "y": -0.3066021502017975,
          "z": -0.15182474255561829
        },
        {
          "x": 0.5375159382820129,
          "y": 0.024273226037621499,
          "z": 0.8429041504859924
        },
        {
          "x": -0.972894012928009,
          "y": 0.0,
          "z": 0.23125141859054566
        },
        {
          "x": -0.9397141933441162,
          "y": 0.0,
          "z": 0.3419609069824219
        }
      ],
      "nextForwards": [
        {
          "x": 0.9284766316413879,
          "y": 0.0,
          "z": -0.3713909387588501
        },
        {
          "x": 0.2425355613231659,
          "y": 0.0,
          "z": -0.9701426029205322
        },
        {
          "x": 0.9284766912460327,
          "y": 0.0,
          "z": 0.37139075994491579
        },
        {
          "x": -0.970142662525177,
          "y": 0.0,
          "z": -0.24253559112548829
        },
        {
          "x": 0.2425355613231659,
          "y": 0.0,
          "z": 0.9701425433158875
        }
      ],
      "offsetAngles": [ 110.86998831707433, 94.85796199852985, 35.67312222489818, 27.406993260880769, 84.03985064211156 ],
      "qualities": [
        {
          "size_quality": 0.0310516357421875,
          "depth_quality": 0.033842828967464679,
          "colorfulness_quality": 0.08644002477761365,
          "covered_quality": 1.0,
          "integrity_quality": 0.978659451007843
        },
        {
          "size_quality": 0.03034210205078125,
          "depth_quality": 0.03273792158168867,
          "colorfulness_quality": 0.08313492861976329,
          "covered_quality": 1.0,
          "integrity_quality": 0.9978047013282776
        },
        {
          "size_quality": 0.031038284301757814,
          "depth_quality": 0.033836499855268788,
          "colorfulness_quality": 0.082275271970293,
          "covered_quality": 1.0,
          "integrity_quality": 0.9785621762275696
        },
        {
          "size_quality": 0.03034210205078125,
          "depth_quality": 0.03273795753403866,
          "colorfulness_quality": 0.071266867942356,
          "covered_quality": 1.0,
          "integrity_quality": 0.9977421164512634
        },
        {
          "size_quality": 0.03033447265625,
          "depth_quality": 0.03273421562073014,
          "colorfulness_quality": 0.07353980807211112,
          "covered_quality": 1.0,
          "integrity_quality": 0.9972097873687744
        }
      ],
      "finalQualities": [ 0.9569092964967052, 0.9500873262816789, 0.9459874870168821, 0.9191810406183913, 0.924909045101503 ]
    },
    {
      "time": "212.9657",
      "teleportTime": "1.075654",
      "teleportType": "auto",
      "exhibition": "AH64 Prefab",
      "prePositions": [
        {
          "x": -0.02154684066772461,
          "y": 1.955174207687378,
          "z": 4.856595039367676
        },
        {
          "x": 0.08582711219787598,
          "y": 2.0330612659454347,
          "z": 4.745918273925781
        },
        {
          "x": 1.335827350616455,
          "y": 2.0330612659454347,
          "z": 4.845917701721191
        },
        {
          "x": -0.3709363043308258,
          "y": 2.0300374031066896,
          "z": 5.179832935333252
        },
        {
          "x": 0.1290636956691742,
          "y": 2.0300374031066896,
          "z": 5.179832935333252
        }
      ],
      "nextPositons": [
        {
          "x": -6.299999713897705,
          "y": 2.0300300121307375,
          "z": -0.12999993562698365
        },
        {
          "x": -5.999999523162842,
          "y": 2.0300300121307375,
          "z": 4.170000076293945
        },
        {
          "x": -4.599999904632568,
          "y": 2.0300300121307375,
          "z": 4.070000171661377
        },
        {
          "x": -6.799999713897705,
          "y": 2.0300300121307375,
          "z": 4.070000171661377
        },
        {
          "x": -7.0,
          "y": 2.0300300121307375,
          "z": 0.070000059902668
        }
      ],
      "preForwards": [
        {
          "x": -0.9170716404914856,
          "y": -0.28557804226875307,
          "z": -0.27825409173965456
        },
        {
          "x": -0.9364570379257202,
          "y": -0.1170470118522644,
          "z": -0.3306786119937897
        },
        {
          "x": -0.9510761499404907,
          "y": 0.012702425941824913,
          "z": -0.30869564414024355
        },
        {
          "x": -0.8232216835021973,
          "y": 0.0,
          "z": -0.5677200555801392
        },
        {
          "x": -0.8446420431137085,
          "y": 0.0,
          "z": -0.5353316068649292
        }
      ],
      "nextForwards": [
        {
          "x": 0.2747211158275604,
          "y": 0.0,
          "z": 0.9615239500999451
        },
        {
          "x": 0.13511307537555695,
          "y": 0.0,
          "z": -0.9908301830291748
        },
        {
          "x": -0.4640069007873535,
          "y": 0.0,
          "z": -0.8858315944671631
        },
        {
          "x": 0.4640069007873535,
          "y": 0.0,
          "z": -0.8858315944671631
        },
        {
          "x": 0.5646839141845703,
          "y": 0.0,
          "z": 0.8253072500228882
        }
      ],
      "offsetAngles": [ 122.82402844761691, 78.31617937158626, 44.37189074391995, 83.05458218245804, 156.74675075272718 ],
      "qualities": [
        {
          "size_quality": 0.1309967041015625,
          "depth_quality": 0.05073216328759086,
          "colorfulness_quality": 0.09708714954556359,
          "covered_quality": 1.0,
          "integrity_quality": 0.964925229549408
        },
        {
          "size_quality": 0.12802505493164063,
          "depth_quality": 0.049610875141413757,
          "colorfulness_quality": 0.09923909270410744,
          "covered_quality": 1.0,
          "integrity_quality": 0.9775855541229248
        },
        {
          "size_quality": 0.11483287811279297,
          "depth_quality": 0.046715390410332829,
          "colorfulness_quality": 0.09676126932874742,
          "covered_quality": 1.0,
          "integrity_quality": 0.9474169015884399
        },
        {
          "size_quality": 0.10930728912353516,
          "depth_quality": 0.044556536909289599,
          "colorfulness_quality": 0.0962130348554347,
          "covered_quality": 1.0,
          "integrity_quality": 0.9659604430198669
        },
        {
          "size_quality": 0.11672496795654297,
          "depth_quality": 0.04624657918563269,
          "colorfulness_quality": 0.0942110186099723,
          "covered_quality": 1.0,
          "integrity_quality": 0.9686290621757507
        }
      ],
      "finalQualities": [ 0.9647134213576194, 0.9698054258200624, 0.9411822323880801, 0.9385392834354993, 0.9426069613241226 ]
    },
    {
      "time": "224.9011",
      "teleportTime": "2.973798",
      "teleportType": "auto",
      "exhibition": "Paint2",
      "prePositions": [
        {
          "x": -2.4087653160095217,
          "y": 1.9617531299591065,
          "z": -4.0790863037109379
        },
        {
          "x": -1.9941728115081788,
          "y": 2.0230612754821779,
          "z": -3.7640817165374758
        },
        {
          "x": -2.0741727352142336,
          "y": 2.0330612659454347,
          "z": -3.744081735610962
        },
        {
          "x": -2.5750794410705568,
          "y": 2.0300374031066896,
          "z": -3.2655513286590578
        },
        {
          "x": -2.0750794410705568,
          "y": 2.0300374031066896,
          "z": -3.2655513286590578
        }
      ],
      "nextPositons": [
        {
          "x": 4.729477882385254,
          "y": 2.0300300121307375,
          "z": -6.6286115646362309
        },
        {
          "x": 3.529477834701538,
          "y": 2.0300300121307375,
          "z": -6.1286115646362309
        },
        {
          "x": 2.729477882385254,
          "y": 2.0300300121307375,
          "z": -6.728611469268799
        },
        {
          "x": 3.029477834701538,
          "y": 2.0300300121307375,
          "z": -5.528611660003662
        },
        {
          "x": 5.829477787017822,
          "y": 2.0300300121307375,
          "z": -7.228611469268799
        }
      ],
      "preForwards": [
        {
          "x": 0.8487704992294312,
          "y": -0.25431472063064577,
          "z": -0.46358758211135867
        },
        {
          "x": 0.8595253229141235,
          "y": -0.1093243882060051,
          "z": -0.49926429986953738
        },
        {
          "x": 0.8975769281387329,
          "y": -0.029899252578616144,
          "z": -0.43984290957450869
        },
        {
          "x": 0.8983466029167175,
          "y": 0.0,
          "z": -0.43928778171539309
        },
        {
          "x": 0.8858311176300049,
          "y": 0.0,
          "z": -0.4640078544616699
        }
      ],
      "nextForwards": [
        {
          "x": -0.44721364974975588,
          "y": 0.0,
          "z": -0.8944272994995117
        },
        {
          "x": 0.12933917343616486,
          "y": 0.0,
          "z": -0.991600513458252
        },
        {
          "x": 0.5432512164115906,
          "y": 0.0,
          "z": -0.8395702838897705
        },
        {
          "x": 0.2659289538860321,
          "y": 0.0,
          "z": -0.9639925956726074
        },
        {
          "x": -0.8574929237365723,
          "y": 0.0,
          "z": -0.514495849609375
        }
      ],
      "offsetAngles": [ 87.9222531550704, 52.41798345370967, 30.98836030529924, 48.51940363751282, 121.39020779955445 ],
      "qualities": [
        {
          "size_quality": 0.6847677230834961,
          "depth_quality": 0.06915044563304843,
          "colorfulness_quality": 0.1958099256611187,
          "covered_quality": 0.9999986290931702,
          "integrity_quality": 0.9963049292564392
        },
        {
          "size_quality": 0.5063104629516602,
          "depth_quality": 0.07311428983031029,
          "colorfulness_quality": 0.1942070013287762,
          "covered_quality": 0.9984158873558044,
          "integrity_quality": 1.001188039779663
        },
        {
          "size_quality": 0.5473594665527344,
          "depth_quality": 0.10864672161597698,
          "colorfulness_quality": 0.22085803608699129,
          "covered_quality": 0.9857269525527954,
          "integrity_quality": 0.8980046510696411
        },
        {
          "size_quality": 0.26488208770751955,
          "depth_quality": 0.04854972040079666,
          "colorfulness_quality": 0.17060861981678938,
          "covered_quality": 0.9801907539367676,
          "integrity_quality": 1.0006449222564698
        },
        {
          "size_quality": 0.49892330169677737,
          "depth_quality": 0.0727893861669801,
          "colorfulness_quality": 0.18744368500265339,
          "covered_quality": 0.9983943700790405,
          "integrity_quality": 0.9999273419380188
        }
      ],
      "finalQualities": [ 0.8903393052606778, 0.8696910273676045, 0.8776523940301959, 0.8046427669373544, 0.8613010861810564 ]
    },
    {
      "time": "298.6892",
      "teleportTime": "12.67488",
      "teleportType": "horseshoe",
      "exhibition": "Car",
      "prePositions": [
        {
          "x": 9.686788558959961,
          "y": 5.134653091430664,
          "z": -1.5033023357391358
        },
        {
          "x": 10.72582721710205,
          "y": 5.103061199188232,
          "z": -1.0615746974945069
        },
        {
          "x": 10.535826683044434,
          "y": 5.453061103820801,
          "z": 0.255918025970459
        },
        {
          "x": 9.10185718536377,
          "y": 5.1633710861206059,
          "z": 0.3514931797981262
        },
        {
          "x": 8.595547676086426,
          "y": 5.1633710861206059,
          "z": -0.9273442625999451
        }
      ],
      "nextPositons": [
        {
          "x": 12.783652305603028,
          "y": 5.1633710861206059,
          "z": -4.355950832366943
        },
        {
          "x": 11.329004287719727,
          "y": 5.1633710861206059,
          "z": -3.98248553276062
        },
        {
          "x": 9.932652473449707,
          "y": 5.1633710861206059,
          "z": -4.535366058349609
        },
        {
          "x": 9.127955436706543,
          "y": 5.1633710861206059,
          "z": -5.80341100692749
        },
        {
          "x": 9.22227954864502,
          "y": 5.1633710861206059,
          "z": -7.302270412445068
        }
      ],
      "preForwards": [
        {
          "x": 0.3708961308002472,
          "y": -0.17989596724510194,
          "z": -0.9110838174819946
        },
        {
          "x": -0.9680505990982056,
          "y": 0.04180411994457245,
          "z": 0.2472458928823471
        },
        {
          "x": -0.13855989277362824,
          "y": -0.23160642385482789,
          "z": -0.9628913998603821
        },
        {
          "x": 0.6160704493522644,
          "y": 0.0,
          "z": -0.7876909971237183
        },
        {
          "x": 0.7737783789634705,
          "y": 0.0,
          "z": -0.6334563493728638
        }
      ],
      "nextForwards": [
        {
          "x": -0.5358132719993591,
          "y": 0.0,
          "z": -0.8443365097045898
        },
        {
          "x": 0.06280669569969177,
          "y": 0.0,
          "z": -0.99802565574646
        },
        {
          "x": 0.6374364495277405,
          "y": 0.0,
          "z": -0.7705029249191284
        },
        {
          "x": 0.9685872793197632,
          "y": 0.0,
          "z": -0.24867451190948487
        },
        {
          "x": 0.9297705888748169,
          "y": 0.0,
          "z": 0.36813944578170779
        }
      ],
      "offsetAngles": [ 54.549992877069829, 107.92832142986072, 47.78957059542108, 37.57116351550849, 60.90650508724593 ],
      "qualities": [
        {
          "size_quality": 0.10598087310791016,
          "depth_quality": 0.030743827029564978,
          "colorfulness_quality": 0.10521273483052783,
          "covered_quality": 1.0,
          "integrity_quality": 0.46847769618034365
        },
        {
          "size_quality": 0.17813968658447267,
          "depth_quality": 0.032065672421755769,
          "colorfulness_quality": 0.11520497165099335,
          "covered_quality": 0.9999892711639404,
          "integrity_quality": 0.9915649890899658
        },
        {
          "size_quality": 0.16475677490234376,
          "depth_quality": 0.02801388047545422,
          "colorfulness_quality": 0.11459202977254388,
          "covered_quality": 0.9999884366989136,
          "integrity_quality": 0.9977476000785828
        },
        {
          "size_quality": 0.15011024475097657,
          "depth_quality": 0.03087655713703119,
          "colorfulness_quality": 0.11687780746777007,
          "covered_quality": 0.9999873042106628,
          "integrity_quality": 0.7317177653312683
        },
        {
          "size_quality": 0.10462760925292969,
          "depth_quality": 0.031013938197906145,
          "colorfulness_quality": 0.10662369102523875,
          "covered_quality": 0.9999908804893494,
          "integrity_quality": 0.49225786328315737
        }
      ],
      "finalQualities": [ 0.6240217111531907, 0.81263917499247, 0.8078819456621817, 0.730162243360595, 0.6327464949687739 ]
    },
    {
      "time": "322.3454",
      "teleportTime": "13.66207",
      "teleportType": "horseshoe",
      "exhibition": "Maitreya",
      "prePositions": [
        {
          "x": 0.6634191274642944,
          "y": 5.148651599884033,
          "z": -4.840782165527344
        },
        {
          "x": 1.7143206596374512,
          "y": 5.203061103820801,
          "z": -4.944081783294678
        },
        {
          "x": 3.215826988220215,
          "y": 5.153061389923096,
          "z": -5.43408203125
        },
        {
          "x": 4.441650867462158,
          "y": 5.1633710861206059,
          "z": -5.5798845291137699
        },
        {
          "x": 5.76283073425293,
          "y": 5.1633710861206059,
          "z": -5.831892967224121
        }
      ],
      "nextPositons": [
        {
          "x": -5.681249618530273,
          "y": 5.1633710861206059,
          "z": -8.616442680358887
        },
        {
          "x": -6.333318710327148,
          "y": 5.1633710861206059,
          "z": -7.430375099182129
        },
        {
          "x": -7.5580058097839359,
          "y": 5.1633710861206059,
          "z": -6.854103088378906
        },
        {
          "x": -8.88752269744873,
          "y": 5.1633710861206059,
          "z": -7.1077423095703129
        },
        {
          "x": -9.81403923034668,
          "y": 5.1633710861206059,
          "z": -8.094411849975586
        }
      ],
      "preForwards": [
        {
          "x": -0.9708086252212524,
          "y": -0.07367730140686035,
          "z": -0.22826038300991059
        },
        {
          "x": -0.8983825445175171,
          "y": 0.24167278409004212,
          "z": 0.36674678325653078
        },
        {
          "x": -0.9837515354156494,
          "y": -0.17815428972244264,
          "z": 0.022223612293601037
        },
        {
          "x": -0.9578344225883484,
          "y": 0.0,
          "z": -0.28732097148895266
        },
        {
          "x": -0.9716509580612183,
          "y": 0.0,
          "z": -0.2364201545715332
        }
      ],
      "nextForwards": [
        {
          "x": -0.9822846055030823,
          "y": 0.0,
          "z": -0.18739581108093263
        },
        {
          "x": -0.6845362782478333,
          "y": 0.0,
          "z": -0.7289791107177734
        },
        {
          "x": -0.125318706035614,
          "y": 0.0,
          "z": -0.9921168088912964
        },
        {
          "x": 0.48176655173301699,
          "y": 0.0,
          "z": -0.8762999773025513
        },
        {
          "x": 0.9048334956169128,
          "y": 0.0,
          "z": -0.4257659912109375
        }
      ],
      "offsetAngles": [ 2.43035251667564, 69.00762863182081, 84.09497026935697, 102.10319452821978, 141.12550688191733 ],
      "qualities": [
        {
          "size_quality": 0.005553245544433594,
          "depth_quality": 0.00643006140156815,
          "colorfulness_quality": 0.0714673524848513,
          "covered_quality": 1.0,
          "integrity_quality": 0.9974306225776672
        },
        {
          "size_quality": 0.005906105041503906,
          "depth_quality": 0.006536097483410544,
          "colorfulness_quality": 0.07647588244918985,
          "covered_quality": 1.0,
          "integrity_quality": 1.0003230571746827
        },
        {
          "size_quality": 0.00888824462890625,
          "depth_quality": 0.009255074839455754,
          "colorfulness_quality": 0.0916596635080647,
          "covered_quality": 1.0,
          "integrity_quality": 1.0046350955963135
        },
        {
          "size_quality": 0.00033283233642578125,
          "depth_quality": 0.0023734085163233458,
          "colorfulness_quality": 0.04722848187089512,
          "covered_quality": 1.0,
          "integrity_quality": 0.017314083874225618
        },
        {
          "size_quality": 0.0,
          "depth_quality": 0.0,
          "colorfulness_quality": 0.043613989192616917,
          "covered_quality": "NaN",
          "integrity_quality": 0.0
        }
      ],
      "finalQualities": [ 0.6984562329142917, 0.7066512719431627, 0.7379992100904196, 0.3611083347692278, "NaN" ]
    },
    {
      "time": "355.424",
      "teleportTime": "10.03872",
      "teleportType": "horseshoe",
      "exhibition": "Paint3",
      "prePositions": [
        {
          "x": -10.978181838989258,
          "y": 5.132627487182617,
          "z": 6.006526947021484
        },
        {
          "x": -10.394172668457032,
          "y": 5.123061180114746,
          "z": 4.685917854309082
        },
        {
          "x": -9.604172706604004,
          "y": 5.163061141967773,
          "z": 3.875917911529541
        },
        {
          "x": -9.006444931030274,
          "y": 5.1633710861206059,
          "z": 2.884958267211914
        },
        {
          "x": -8.302079200744629,
          "y": 5.1633710861206059,
          "z": 2.0335512161254885
        }
      ],
      "nextPositons": [
        {
          "x": -10.317502975463868,
          "y": 5.1633710861206059,
          "z": 7.693806171417236
        },
        {
          "x": -9.118414878845215,
          "y": 5.1633710861206059,
          "z": 7.304218769073486
        },
        {
          "x": -7.919339179992676,
          "y": 5.1633710861206059,
          "z": 7.693841934204102
        },
        {
          "x": -7.178281307220459,
          "y": 5.1633710861206059,
          "z": 8.713851928710938
        },
        {
          "x": -7.178299903869629,
          "y": 5.1633710861206059,
          "z": 9.974641799926758
        }
      ],
      "preForwards": [
        {
          "x": 0.4793539345264435,
          "y": -0.18736211955547334,
          "z": 0.8573886156082153
        },
        {
          "x": -0.18244320154190064,
          "y": -0.18187259137630464,
          "z": 0.9662488698959351
        },
        {
          "x": 0.048018623143434528,
          "y": -0.18031692504882813,
          "z": 0.9824357628822327
        },
        {
          "x": -0.2630341053009033,
          "y": 0.0,
          "z": 0.9647865295410156
        },
        {
          "x": -0.33543646335601809,
          "y": 0.0,
          "z": 0.9420628547668457
        }
      ],
      "nextForwards": [
        {
          "x": 0.587773323059082,
          "y": 0.0,
          "z": 0.8090256452560425
        },
        {
          "x": -0.000014960765838623047,
          "y": 0.0,
          "z": 1.0
        },
        {
          "x": -0.587797224521637,
          "y": 0.0,
          "z": 0.8090083003044128
        },
        {
          "x": -0.9510608911514282,
          "y": 0.0,
          "z": 0.3090032935142517
        },
        {
          "x": -0.9510518312454224,
          "y": 0.0,
          "z": -0.30903124809265139
        }
      ],
      "offsetAngles": [ 6.790238619044828, 10.691611982644816, 38.79907103316441, 56.750652532579128, 88.4017802517269 ],
      "qualities": [
        {
          "size_quality": 0.1599559783935547,
          "depth_quality": 0.034095957110709739,
          "colorfulness_quality": 0.1068533725583799,
          "covered_quality": 0.9999940395355225,
          "integrity_quality": 0.490266352891922
        },
        {
          "size_quality": 0.2936439514160156,
          "depth_quality": 0.038901682182210139,
          "colorfulness_quality": 0.1223404250489242,
          "covered_quality": 1.0,
          "integrity_quality": 0.704092264175415
        },
        {
          "size_quality": 0.3293495178222656,
          "depth_quality": 0.037315046827292187,
          "colorfulness_quality": 0.12913589661467662,
          "covered_quality": 0.999997079372406,
          "integrity_quality": 0.999565839767456
        },
        {
          "size_quality": 0.2573719024658203,
          "depth_quality": 0.03851410306170165,
          "colorfulness_quality": 0.11315459808787523,
          "covered_quality": 0.9999963045120239,
          "integrity_quality": 0.6260706186294556
        },
        {
          "size_quality": 0.10486316680908203,
          "depth_quality": 0.028280559737115218,
          "colorfulness_quality": 0.08983449359095985,
          "covered_quality": 1.0,
          "integrity_quality": 0.38210558891296389
        }
      ],
      "finalQualities": [ 0.6143915368048508, 0.7157627621917175, 0.8157211152380699, 0.6758043200914157, 0.5509347677180643 ]
    },
    {
      "time": "380.421",
      "teleportTime": "7.723947",
      "teleportType": "horseshoe",
      "exhibition": "Vase1",
      "prePositions": [
        {
          "x": -0.6675254106521606,
          "y": 5.13232421875,
          "z": 10.184764862060547
        },
        {
          "x": -1.4841728210449219,
          "y": 5.153061389923096,
          "z": 10.40591812133789
        },
        {
          "x": -2.6241726875305177,
          "y": 5.1363935470581059,
          "z": 10.785918235778809
        },
        {
          "x": -3.610537052154541,
          "y": 5.1633710861206059,
          "z": 10.96275806427002
        },
        {
          "x": -4.666297912597656,
          "y": 5.1633710861206059,
          "z": 11.233809471130371
        }
      ],
      "nextPositons": [
        {
          "x": 2.9663493633270265,
          "y": 5.1633710861206059,
          "z": 11.050721168518067
        },
        {
          "x": 3.147029399871826,
          "y": 5.1633710861206059,
          "z": 10.103670120239258
        },
        {
          "x": 3.849865436553955,
          "y": 5.1633710861206059,
          "z": 9.443689346313477
        },
        {
          "x": 4.806398391723633,
          "y": 5.1633710861206059,
          "z": 9.322871208190918
        },
        {
          "x": 5.6512651443481449,
          "y": 5.1633710861206059,
          "z": 9.787363052368164
        }
      ],
      "preForwards": [
        {
          "x": 0.9816427230834961,
          "y": -0.1847352534532547,
          "z": 0.04744355008006096
        },
        {
          "x": 0.9959821105003357,
          "y": -0.07953010499477387,
          "z": -0.041166309267282489
        },
        {
          "x": 0.9219387769699097,
          "y": -0.3872388005256653,
          "z": -0.008661769330501557
        },
        {
          "x": 0.9999105930328369,
          "y": 0.0,
          "z": 0.013373374938964844
        },
        {
          "x": 0.9997124671936035,
          "y": 0.0,
          "z": -0.02398061752319336
        }
      ],
      "nextForwards": [
        {
          "x": 0.9921174049377441,
          "y": 0.0,
          "z": -0.12531280517578126
        },
        {
          "x": 0.8762969970703125,
          "y": 0.0,
          "z": 0.48177123069763186
        },
        {
          "x": 0.4257608950138092,
          "y": 0.0,
          "z": 0.9048357009887695
        },
        {
          "x": -0.18740133941173554,
          "y": 0.0,
          "z": 0.9822834134101868
        },
        {
          "x": -0.7289827466011047,
          "y": 0.0,
          "z": 0.6845321655273438
        }
      ],
      "offsetAngles": [ 9.965828389004514, 31.167970376905033, 65.33945500468008, 100.03491077055969, 138.17530225814154 ],
      "qualities": [
        {
          "size_quality": 0.030022621154785157,
          "depth_quality": 0.040084160772543477,
          "colorfulness_quality": 0.10518254847030353,
          "covered_quality": 1.0,
          "integrity_quality": 0.576554000377655
        },
        {
          "size_quality": 0.02752971649169922,
          "depth_quality": 0.02870484000079208,
          "colorfulness_quality": 0.0936146215978404,
          "covered_quality": 1.0,
          "integrity_quality": 1.0001039505004883
        },
        {
          "size_quality": 0.01805400848388672,
          "depth_quality": 0.01934579930929893,
          "colorfulness_quality": 0.07716631378937372,
          "covered_quality": 1.0,
          "integrity_quality": 0.998839259147644
        },
        {
          "size_quality": 0.015595436096191407,
          "depth_quality": 0.016912773952093765,
          "colorfulness_quality": 0.06923544901220019,
          "covered_quality": 1.0,
          "integrity_quality": 0.999633252620697
        },
        {
          "size_quality": 0.017992019653320314,
          "depth_quality": 0.019370983989362088,
          "colorfulness_quality": 0.0682230856436532,
          "covered_quality": 1.0,
          "integrity_quality": 0.9994173049926758
        }
      ],
      "finalQualities": [ 0.8361949076340869, 0.9138048103476577, 0.8334029790429902, 0.8055859964722101, 0.8156020825587129 ]
    },
    {
      "time": "408.0572",
      "teleportTime": "11.15092",
      "teleportType": "horseshoe",
      "exhibition": "Paint4",
      "prePositions": [
        {
          "x": 12.438883781433106,
          "y": 5.132787704467773,
          "z": 5.448457717895508
        },
        {
          "x": 11.525826454162598,
          "y": 5.153061389923096,
          "z": 6.125918388366699
        },
        {
          "x": 10.63582706451416,
          "y": 5.153061389923096,
          "z": 6.775918006896973
        },
        {
          "x": 9.607831954956055,
          "y": 5.1633710861206059,
          "z": 7.573794364929199
        },
        {
          "x": 8.64103889465332,
          "y": 5.1633710861206059,
          "z": 8.276172637939454
        }
      ],
      "nextPositons": [
        {
          "x": 13.79261589050293,
          "y": 5.1633710861206059,
          "z": 4.261998176574707
        },
        {
          "x": 12.985467910766602,
          "y": 5.1633710861206059,
          "z": 3.594233512878418
        },
        {
          "x": 12.724973678588868,
          "y": 5.1633710861206059,
          "z": 2.579571008682251
        },
        {
          "x": 13.11063289642334,
          "y": 5.1633710861206059,
          "z": 1.605576992034912
        },
        {
          "x": 13.995138168334961,
          "y": 5.1633710861206059,
          "z": 1.0442841053009034
        }
      ],
      "preForwards": [
        {
          "x": 0.6011506915092468,
          "y": -0.17613855004310609,
          "z": -0.7794827818870544
        },
        {
          "x": 0.838683545589447,
          "y": -0.22032573819160462,
          "z": -0.49806302785873415
        },
        {
          "x": 0.8077249526977539,
          "y": -0.14789749681949616,
          "z": -0.570707380771637
        },
        {
          "x": 0.7841514348983765,
          "y": 0.0,
          "z": -0.6205694675445557
        },
        {
          "x": 0.7888034582138062,
          "y": 0.0,
          "z": -0.6146457195281982
        }
      ],
      "nextForwards": [
        {
          "x": 0.3681478500366211,
          "y": 0.0,
          "z": -0.9297674894332886
        },
        {
          "x": 0.8443414568901062,
          "y": 0.0,
          "z": -0.5358058214187622
        },
        {
          "x": 0.9980252385139465,
          "y": 0.0,
          "z": 0.06281524896621704
        },
        {
          "x": 0.7704974412918091,
          "y": 0.0,
          "z": 0.6374430656433106
        },
        {
          "x": 0.24866554141044618,
          "y": 0.0,
          "z": 0.9685894250869751
        }
      ],
      "offsetAngles": [ 16.038624783030288, 1.694081701050898, 38.84497673511191, 77.95915171912384, 113.5276217843375 ],
      "qualities": [
        {
          "size_quality": 0.3502473831176758,
          "depth_quality": 0.08671954321418728,
          "colorfulness_quality": 0.177053900224546,
          "covered_quality": 1.0,
          "integrity_quality": 0.4561874568462372
        },
        {
          "size_quality": 0.6285381317138672,
          "depth_quality": 0.07057852084791566,
          "colorfulness_quality": 0.19704322258995517,
          "covered_quality": 1.0,
          "integrity_quality": 0.6079891920089722
        },
        {
          "size_quality": 0.9342823028564453,
          "depth_quality": 0.0334862040596046,
          "colorfulness_quality": 0.2129884187118377,
          "covered_quality": 1.0,
          "integrity_quality": 0.7356147766113281
        },
        {
          "size_quality": 0.8043251037597656,
          "depth_quality": 0.052754985210003147,
          "colorfulness_quality": 0.20582903537719145,
          "covered_quality": 1.0,
          "integrity_quality": 0.7294418811798096
        },
        {
          "size_quality": 0.5365610122680664,
          "depth_quality": 0.0753853648528392,
          "colorfulness_quality": 0.1903837439153923,
          "covered_quality": 1.0,
          "integrity_quality": 0.5662114024162293
        }
      ],
      "finalQualities": [ 0.6648237960884169, 0.7562080279790359, 0.8333565783534644, 0.8154289819422218, 0.7282593702250448 ]
    },
    {
      "time": "416.7076",
      "teleportTime": "1.281038",
      "teleportType": "auto",
      "exhibition": "Car",
      "prePositions": [
        {
          "x": 12.394933700561524,
          "y": 5.150321960449219,
          "z": 6.403495788574219
        },
        {
          "x": 12.845745086669922,
          "y": 5.183061122894287,
          "z": 3.780958652496338
        },
        {
          "x": 12.845827102661133,
          "y": 5.17114782333374,
          "z": 2.505918025970459
        },
        {
          "x": 13.11063289642334,
          "y": 5.1633710861206059,
          "z": 1.605576992034912
        },
        {
          "x": 13.995138168334961,
          "y": 5.1633710861206059,
          "z": 1.0442841053009034
        }
      ],
      "nextPositons": [
        {
          "x": 11.723000526428223,
          "y": 5.163370132446289,
          "z": -5.0450005531311039
        },
        {
          "x": 10.92300033569336,
          "y": 5.163370132446289,
          "z": -5.145000457763672
        },
        {
          "x": 12.42300033569336,
          "y": 5.163370132446289,
          "z": -5.0450005531311039
        },
        {
          "x": 13.123000144958496,
          "y": 5.163370132446289,
          "z": -4.74500036239624
        },
        {
          "x": 10.223000526428223,
          "y": 5.163370132446289,
          "z": -5.445000171661377
        }
      ],
      "preForwards": [
        {
          "x": 0.24895627796649934,
          "y": -0.026981845498085023,
          "z": -0.9681394100189209
        },
        {
          "x": 0.30426689982414248,
          "y": -0.12105497717857361,
          "z": 0.9448636770248413
        },
        {
          "x": -0.3884596824645996,
          "y": -0.12430603802204132,
          "z": -0.9130427837371826
        },
        {
          "x": -0.2268187552690506,
          "y": 0.0,
          "z": -0.9739371538162231
        },
        {
          "x": -0.4132155179977417,
          "y": 0.0,
          "z": -0.9106332063674927
        }
      ],
      "nextForwards": [
        {
          "x": 0.27881014347076418,
          "y": 0.0,
          "z": -0.9603463411331177
        },
        {
          "x": 0.49301254749298098,
          "y": 0.0,
          "z": -0.8700224161148071
        },
        {
          "x": 0.06438222527503967,
          "y": 0.0,
          "z": -0.9979254007339478
        },
        {
          "x": -0.1454939991235733,
          "y": 0.0,
          "z": -0.9893592596054077
        },
        {
          "x": 0.6643638014793396,
          "y": 0.0,
          "z": -0.7474095821380615
        }
      ],
      "offsetAngles": [ 1.768128956646109, 132.61152571795265, 26.739016120181988, 4.743921176898738, 66.04051245946266 ],
      "qualities": [
        {
          "size_quality": 0.30127525329589846,
          "depth_quality": 0.05336272754580446,
          "colorfulness_quality": 0.13020273732192795,
          "covered_quality": 1.0,
          "integrity_quality": 0.9216007590293884
        },
        {
          "size_quality": 0.28021240234375,
          "depth_quality": 0.04692875301665332,
          "colorfulness_quality": 0.129041343607562,
          "covered_quality": 0.9999966025352478,
          "integrity_quality": 0.9615792632102966
        },
        {
          "size_quality": 0.3013486862182617,
          "depth_quality": 0.058428053591254438,
          "colorfulness_quality": 0.12913431725368569,
          "covered_quality": 1.0,
          "integrity_quality": 0.8787864446640015
        },
        {
          "size_quality": 0.24244117736816407,
          "depth_quality": 0.04990901496122201,
          "colorfulness_quality": 0.11866237152470799,
          "covered_quality": 0.9999960660934448,
          "integrity_quality": 0.962411105632782
        },
        {
          "size_quality": 0.26738452911376955,
          "depth_quality": 0.04351741634983234,
          "colorfulness_quality": 0.12715231247675949,
          "covered_quality": 1.0,
          "integrity_quality": 0.9480997323989868
        }
      ],
      "finalQualities": [ 0.857852288629309, 0.8589571809276912, 0.8462645705895353, 0.8355819111945695, 0.8470976984840926 ]
    },
    {
      "time": "426.312",
      "teleportTime": "0.82177",
      "teleportType": "auto",
      "exhibition": "Maitreya",
      "prePositions": [
        {
          "x": -0.16894924640655518,
          "y": 5.151270866394043,
          "z": -4.982641220092773
        },
        {
          "x": 0.3658270835876465,
          "y": 5.163061141967773,
          "z": -4.884081840515137
        },
        {
          "x": 0.8158273696899414,
          "y": 5.163061141967773,
          "z": -4.854081630706787
        },
        {
          "x": -0.12467901408672333,
          "y": 5.1633710861206059,
          "z": -4.393515110015869
        },
        {
          "x": 0.3753209710121155,
          "y": 5.1633710861206059,
          "z": -4.393515110015869
        }
      ],
      "nextPositons": [
        {
          "x": -8.862000465393067,
          "y": 5.163370132446289,
          "z": -8.241000175476075
        },
        {
          "x": -9.66200065612793,
          "y": 5.163370132446289,
          "z": -8.3410005569458
        },
        {
          "x": -10.562000274658204,
          "y": 5.163370132446289,
          "z": -9.541000366210938
        },
        {
          "x": -8.16200065612793,
          "y": 5.163370132446289,
          "z": -8.541000366210938
        },
        {
          "x": -10.26200008392334,
          "y": 5.163370132446289,
          "z": -8.8410005569458
        }
      ],
      "preForwards": [
        {
          "x": -0.8852168917655945,
          "y": -0.02889253944158554,
          "z": -0.4642803966999054
        },
        {
          "x": -0.898931086063385,
          "y": -0.030145732685923578,
          "z": -0.43705159425735476
        },
        {
          "x": -0.925986111164093,
          "y": -0.1135886013507843,
          "z": -0.36006584763526919
        },
        {
          "x": -0.7491529583930969,
          "y": 0.0,
          "z": -0.6623972654342651
        },
        {
          "x": -0.7716298699378967,
          "y": 0.0,
          "z": -0.6360719203948975
        }
      ],
      "nextForwards": [
        {
          "x": -0.13216359913349152,
          "y": 0.0,
          "z": -0.9912279844284058
        },
        {
          "x": 0.3939196765422821,
          "y": 0.0,
          "z": -0.9191449880599976
        },
        {
          "x": 0.9912279844284058,
          "y": 0.0,
          "z": -0.13216376304626466
        },
        {
          "x": -0.5999999046325684,
          "y": 0.0,
          "z": -0.8000000715255737
        },
        {
          "x": 0.8000000715255737,
          "y": 0.0,
          "z": -0.5999999046325684
        }
      ],
      "offsetAngles": [ 54.72916240146901, 87.2700383836127, 151.15699217263228, 11.64714692094691, 103.63058193881443 ],
      "qualities": [
        {
          "size_quality": 0.03650474548339844,
          "depth_quality": 0.03763892826580127,
          "colorfulness_quality": 0.15935796634910516,
          "covered_quality": 0.9668739438056946,
          "integrity_quality": 0.98746258020401
        },
        {
          "size_quality": 0.03633594512939453,
          "depth_quality": 0.03714667117607961,
          "colorfulness_quality": 0.17489838361820768,
          "covered_quality": 1.0,
          "integrity_quality": 0.9894307851791382
        },
        {
          "size_quality": 0.032362937927246097,
          "depth_quality": 0.036021814972948349,
          "colorfulness_quality": 0.1761404156242019,
          "covered_quality": 1.0,
          "integrity_quality": 0.9630228877067566
        },
        {
          "size_quality": 0.035376548767089847,
          "depth_quality": 0.03786573952553892,
          "colorfulness_quality": 0.13998832678149374,
          "covered_quality": 1.0,
          "integrity_quality": 0.9584528207778931
        },
        {
          "size_quality": 0.035544395446777347,
          "depth_quality": 0.037500873892426209,
          "colorfulness_quality": 0.18223581361112169,
          "covered_quality": 1.0,
          "integrity_quality": 0.9602957963943481
        }
      ],
      "finalQualities": [ 0.9142259090011907, 0.9428981442872622, 0.9241094693315382, 0.8883238742207309, 0.9414921613111496 ]
    },
    {
      "time": "439.0231",
      "teleportTime": "3.498277",
      "teleportType": "auto",
      "exhibition": "Paint3",
      "prePositions": [
        {
          "x": -14.780704498291016,
          "y": 5.150859832763672,
          "z": -2.554661512374878
        },
        {
          "x": -14.36417293548584,
          "y": 5.163061141967773,
          "z": -1.9440817832946778
        },
        {
          "x": -14.284172058105469,
          "y": 5.163061141967773,
          "z": -2.0040817260742189
        },
        {
          "x": -15.122876167297364,
          "y": 5.1633710861206059,
          "z": -1.4965872764587403
        },
        {
          "x": -14.622876167297364,
          "y": 5.1633710861206059,
          "z": -1.4965872764587403
        }
      ],
      "nextPositons": [
        {
          "x": -9.250824928283692,
          "y": 5.163370132446289,
          "z": 8.61844539642334
        },
        {
          "x": -10.650825500488282,
          "y": 5.163370132446289,
          "z": 7.918445110321045
        },
        {
          "x": -8.450824737548829,
          "y": 5.163370132446289,
          "z": 8.61844539642334
        },
        {
          "x": -11.750824928283692,
          "y": 5.163370132446289,
          "z": 6.418445110321045
        },
        {
          "x": -5.750824928283691,
          "y": 5.163370132446289,
          "z": 10.11844539642334
        }
      ],
      "preForwards": [
        {
          "x": 0.34091296792030337,
          "y": -0.03702818229794502,
          "z": 0.9393653869628906
        },
        {
          "x": 0.49191033840179446,
          "y": -0.050063490867614749,
          "z": 0.8692052960395813
        },
        {
          "x": 0.5553879141807556,
          "y": -0.17879796028137208,
          "z": 0.8121426105499268
        },
        {
          "x": 0.4146106243133545,
          "y": 0.0,
          "z": 0.909998893737793
        },
        {
          "x": 0.3808736801147461,
          "y": 0.0,
          "z": 0.9246270656585693
        }
      ],
      "nextForwards": [
        {
          "x": -0.34174323081970217,
          "y": 0.0,
          "z": 0.9397933483123779
        },
        {
          "x": 0.202605739235878,
          "y": 0.0,
          "z": 0.9792603850364685
        },
        {
          "x": -0.5881718397140503,
          "y": 0.0,
          "z": 0.8087359666824341
        },
        {
          "x": 0.3603992462158203,
          "y": 0.0,
          "z": 0.9327981472015381
        },
        {
          "x": -0.9870073795318604,
          "y": 0.0,
          "z": 0.16067546606063844
        }
      ],
      "offsetAngles": [ 39.92988399554065, 17.817503176895003, 70.39385652119108, 3.3701101446976624, 103.14170431307503 ],
      "qualities": [
        {
          "size_quality": 0.7694902420043945,
          "depth_quality": 0.0543057719478198,
          "colorfulness_quality": 0.16639313918171515,
          "covered_quality": 0.9810650944709778,
          "integrity_quality": 0.891225278377533
        },
        {
          "size_quality": 0.513026237487793,
          "depth_quality": 0.0606459861888381,
          "colorfulness_quality": 0.14373995445726724,
          "covered_quality": 0.99482661485672,
          "integrity_quality": 0.9977039694786072
        },
        {
          "size_quality": 0.6279563903808594,
          "depth_quality": 0.053601854664208897,
          "colorfulness_quality": 0.15695450000730783,
          "covered_quality": 0.9851729869842529,
          "integrity_quality": 0.9878124594688416
        },
        {
          "size_quality": 0.15423011779785157,
          "depth_quality": 0.02508078983738236,
          "colorfulness_quality": 0.10192159059128009,
          "covered_quality": 0.9743448495864868,
          "integrity_quality": 0.998271644115448
        },
        {
          "size_quality": 0.1775960922241211,
          "depth_quality": 0.02944121610767954,
          "colorfulness_quality": 0.11031951775095299,
          "covered_quality": 0.9781981706619263,
          "integrity_quality": 1.0003491640090943
        }
      ],
      "finalQualities": [ 0.8864606444271915, 0.8624568191381394, 0.8862392470389002, 0.7460566107002628, 0.763422791564619 ]
    },
    {
      "time": "463.4556",
      "teleportTime": "5.075856",
      "teleportType": "auto",
      "exhibition": "Vase1",
      "prePositions": [
        {
          "x": 6.961276054382324,
          "y": 5.123476982116699,
          "z": 11.115774154663086
        },
        {
          "x": 7.455826759338379,
          "y": 5.163061141967773,
          "z": 11.265917778015137
        },
        {
          "x": 7.7958269119262699,
          "y": 5.153061389923096,
          "z": 11.159858703613282
        },
        {
          "x": 6.85835075378418,
          "y": 5.1633710861206059,
          "z": 12.22940731048584
        },
        {
          "x": 4.875999927520752,
          "y": 5.163370132446289,
          "z": 9.970999717712403
        }
      ],
      "nextPositons": [
        {
          "x": 3.675999879837036,
          "y": 5.163370132446289,
          "z": 10.071000099182129
        },
        {
          "x": 3.0759999752044679,
          "y": 5.163370132446289,
          "z": 12.571000099182129
        },
        {
          "x": 2.875999927520752,
          "y": 5.163370132446289,
          "z": 10.871000289916993
        },
        {
          "x": 4.875999927520752,
          "y": 5.163370132446289,
          "z": 9.970999717712403
        },
        {
          "x": 2.7760000228881838,
          "y": 5.163370132446289,
          "z": 11.871000289916993
        }
      ],
      "preForwards": [
        {
          "x": -0.970475971698761,
          "y": -0.23907120525836945,
          "z": 0.031959958374500278
        },
        {
          "x": 0.5445799231529236,
          "y": -0.0637056976556778,
          "z": -0.8362860679626465
        },
        {
          "x": -0.968924343585968,
          "y": -0.21877659857273103,
          "z": -0.11542476713657379
        },
        {
          "x": -0.9837359189987183,
          "y": 0.0,
          "z": 0.1796208620071411
        },
        {
          "x": -0.5696694850921631,
          "y": 0.0,
          "z": 0.8218739032745361
        }
      ],
      "nextForwards": [
        {
          "x": 0.42288559675216677,
          "y": 0.0,
          "z": 0.906183123588562
        },
        {
          "x": 0.7926241159439087,
          "y": 0.0,
          "z": -0.6097108125686646
        },
        {
          "x": 0.9061831831932068,
          "y": 0.0,
          "z": 0.4228854179382324
        },
        {
          "x": -0.2982749044895172,
          "y": 0.0,
          "z": 0.954479992389679
        },
        {
          "x": 0.9828721880912781,
          "y": 0.0,
          "z": -0.1842886209487915
        }
      ],
      "offsetAngles": [ 113.1307058266566, 19.359700145330409, 161.77657041812837, 62.298306411043999, 135.3468389275531 ],
      "qualities": [
        {
          "size_quality": 0.030045509338378907,
          "depth_quality": 0.03267430295295912,
          "colorfulness_quality": 0.09013410476952516,
          "covered_quality": 1.0,
          "integrity_quality": 0.9892922043800354
        },
        {
          "size_quality": 0.030055999755859376,
          "depth_quality": 0.03256667823828866,
          "colorfulness_quality": 0.11187445871799495,
          "covered_quality": 1.0,
          "integrity_quality": 0.9927237033843994
        },
        {
          "size_quality": 0.029908180236816407,
          "depth_quality": 0.03239942458951043,
          "colorfulness_quality": 0.10210138207903566,
          "covered_quality": 1.0,
          "integrity_quality": 0.995397686958313
        },
        {
          "size_quality": 0.029898643493652345,
          "depth_quality": 0.03228716711833716,
          "colorfulness_quality": 0.07787539150518889,
          "covered_quality": 1.0,
          "integrity_quality": 0.9979627728462219
        },
        {
          "size_quality": 0.030361175537109376,
          "depth_quality": 0.03304900088120783,
          "colorfulness_quality": 0.11039830697319986,
          "covered_quality": 1.0,
          "integrity_quality": 0.9819561243057251
        }
      ],
      "finalQualities": [ 0.918195362537815, 0.9623091172443374, 0.9429076060779762, 0.8953373474278819, 0.9579670471588524 ]
    },
    {
      "time": "466.8869",
      "teleportTime": "1.041443",
      "teleportType": "auto",
      "exhibition": "Paint4",
      "prePositions": [
        {
          "x": 4.263690948486328,
          "y": 5.151264667510986,
          "z": 9.404586791992188
        },
        {
          "x": 3.075827121734619,
          "y": 5.153061389923096,
          "z": 12.595918655395508
        },
        {
          "x": 2.585827350616455,
          "y": 5.163061141967773,
          "z": 10.675917625427246
        },
        {
          "x": 4.875999927520752,
          "y": 5.163370132446289,
          "z": 9.970999717712403
        },
        {
          "x": 2.7760000228881838,
          "y": 5.163370132446289,
          "z": 11.871000289916993
        }
      ],
      "nextPositons": [
        {
          "x": 11.78921890258789,
          "y": 5.163370132446289,
          "z": 1.8752813339233399
        },
        {
          "x": 12.28921890258789,
          "y": 5.163370132446289,
          "z": 1.275281310081482
        },
        {
          "x": 13.78921890258789,
          "y": 5.163370132446289,
          "z": -0.824718713760376
        },
        {
          "x": 12.28921890258789,
          "y": 5.163370132446289,
          "z": 4.37528133392334
        },
        {
          "x": 11.8892183303833,
          "y": 5.163370132446289,
          "z": 5.075281143188477
        }
      ],
      "preForwards": [
        {
          "x": 0.8145887851715088,
          "y": -0.030427243560552598,
          "z": -0.5792402625083923
        },
        {
          "x": 0.7987637519836426,
          "y": -0.13689103722572328,
          "z": -0.5858646631240845
        },
        {
          "x": 0.9066736102104187,
          "y": -0.25815123319625857,
          "z": 0.33361804485321047
        },
        {
          "x": 0.8748824000358582,
          "y": 0.0,
          "z": -0.48433566093444826
        },
        {
          "x": 0.8472875356674194,
          "y": 0.0,
          "z": -0.5311344861984253
        }
      ],
      "nextForwards": [
        {
          "x": 0.9847836494445801,
          "y": 0.0,
          "z": 0.1737852692604065
        },
        {
          "x": 0.9240168333053589,
          "y": 0.0,
          "z": 0.382351815700531
        },
        {
          "x": 0.39054974913597109,
          "y": 0.0,
          "z": 0.9205818176269531
        },
        {
          "x": 0.836461067199707,
          "y": 0.0,
          "z": -0.5480263233184815
        },
        {
          "x": 0.7854918241500855,
          "y": 0.0,
          "z": -0.6188722848892212
        }
      ],
      "offsetAngles": [ 45.42396528462518, 58.738152226887908, 46.80977994754585, 4.262780874918803, 6.151667577500319 ],
      "qualities": [
        {
          "size_quality": 0.6156206130981445,
          "depth_quality": 0.04269967396781998,
          "colorfulness_quality": 0.20381038943840894,
          "covered_quality": 0.9983099102973938,
          "integrity_quality": 0.9802261590957642
        },
        {
          "size_quality": 0.7234506607055664,
          "depth_quality": 0.04266561824635378,
          "colorfulness_quality": 0.2141768830057496,
          "covered_quality": 1.0,
          "integrity_quality": 0.952624499797821
        },
        {
          "size_quality": 0.5375585556030273,
          "depth_quality": 0.05354153073293805,
          "colorfulness_quality": 0.20302368332411958,
          "covered_quality": 1.0,
          "integrity_quality": 0.9811915755271912
        },
        {
          "size_quality": 0.5505685806274414,
          "depth_quality": 0.05896297796452443,
          "colorfulness_quality": 0.19578181284207886,
          "covered_quality": 0.9964507818222046,
          "integrity_quality": 0.962052047252655
        },
        {
          "size_quality": 0.3082466125488281,
          "depth_quality": 0.041649500300853407,
          "colorfulness_quality": 0.17651092355277107,
          "covered_quality": 0.9696398973464966,
          "integrity_quality": 1.0007244348526
        }
      ],
      "finalQualities": [ 0.8614478490448247, 0.8763611947958085, 0.8556650172715152, 0.845319258428324, 0.7965932594742829 ]
    }
  ]
}
